llamda_cli/__init__.py
llamda_cli/lld/__init__.py
llamda_cli/lld/cli/__init__.py
llamda_cli/lld/cli/lld_cli.py
llamda_cli/lld/cli/option_decorators.py
llamda_cli/lld/files/__init__.py
llamda_cli/lld/files/files.py
llamda_cli/lld/files/template.jinja2
llamda_cli/lld/utils/__init__.py
llamda_cli/lld/utils/console.py
llamda_cli/lld/utils/files.py
llamda_cli/lld/utils/git.py
llamda_cli/lld/utils/template.py
llamda_cli-0.3.0.dist-info/LICENSE
llamda_cli-0.3.0.dist-info/METADATA
llamda_cli-0.3.0.dist-info/WHEEL
llamda_cli-0.3.0.dist-info/entry_points.txt
llamda_cli-0.3.0.dist-info/RECORD
