Metadata-Version: 2.1
Name: llamda-cli
Version: 0.3.0
Summary: Collects docs from a doc folder into a single xml file for use by claude
License: MIT
Author: lumpenspace
Author-email: 125578322+lumpenspace@users.noreply.github.com
Requires-Python: >=3.11,<4.0
Classifier: License :: OSI Approved :: MIT License
Classifier: Programming Language :: Python :: 3
Classifier: Programming Language :: Python :: 3.11
Classifier: Programming Language :: Python :: 3.12
Requires-Dist: Jinja2 (>=3.1.4,<4.0.0)
Requires-Dist: click (>=8.1.7,<9.0.0)
Requires-Dist: console (>=0.9907,<0.9908)
Requires-Dist: gitpython (>=3.1.43,<4.0.0)
Requires-Dist: rich (>=13.7.1,<14.0.0)
Requires-Dist: rich-click (>=1.8.3,<2.0.0)
